odoo8_addon_social_media_pinterest_blog-8.0.1.0.0-py2.7-nspkg.pth
odoo8_addon_social_media_pinterest_blog-8.0.1.0.0.dist-info/DESCRIPTION.rst
odoo8_addon_social_media_pinterest_blog-8.0.1.0.0.dist-info/METADATA
odoo8_addon_social_media_pinterest_blog-8.0.1.0.0.dist-info/RECORD
odoo8_addon_social_media_pinterest_blog-8.0.1.0.0.dist-info/WHEEL
odoo8_addon_social_media_pinterest_blog-8.0.1.0.0.dist-info/metadata.json
odoo8_addon_social_media_pinterest_blog-8.0.1.0.0.dist-info/namespace_packages.txt
odoo8_addon_social_media_pinterest_blog-8.0.1.0.0.dist-info/top_level.txt
odoo_addons/social_media_pinterest_blog/README.rst
odoo_addons/social_media_pinterest_blog/__init__.py
odoo_addons/social_media_pinterest_blog/__openerp__.py
odoo_addons/social_media_pinterest_blog/static/description/icon.png
odoo_addons/social_media_pinterest_blog/static/description/index.html
odoo_addons/social_media_pinterest_blog/static/description/pinterest.png
odoo_addons/social_media_pinterest_blog/static/description/settings.png
odoo_addons/social_media_pinterest_blog/views/website_blog_template.xml
